minorminer/_minorminer.cpp
minorminer/__init__.py
minorminer/busclique.cpp
minorminer/subgraph.cpython-312-x86_64-linux-gnu.so
minorminer/_minorminer.cpython-312-x86_64-linux-gnu.so
minorminer/busclique.pyx
minorminer/_minorminer_h.pxi
minorminer/minorminer.py
minorminer/_minorminer.pyx
minorminer/subgraph.cpp
minorminer/subgraph.pyx
minorminer/busclique.cpython-312-x86_64-linux-gnu.so
minorminer/busclique_h.pxi
minorminer/_extern/__init__.pyx
minorminer/_extern/rpack/__init__.py
minorminer/_extern/rpack/_core.cpython-312-x86_64-linux-gnu.so
minorminer/_extern/rpack/_core.c
minorminer/_extern/rpack/_core.pyx
minorminer/_extern/rpack/_core.pxd
minorminer/_extern/rpack/LICENSE.md
minorminer/_extern/rpack/include/rpackcore.h
minorminer/_extern/rpack/src/rpackcore.c
minorminer/layout/__init__.py
minorminer/layout/layout.py
minorminer/layout/placement.py
minorminer/utils/__init__.py
minorminer/utils/parallel_embeddings.py
minorminer/utils/pegasus.py
minorminer/utils/exceptions.py
minorminer/utils/polynomialembedder.py
minorminer/utils/zephyr.py
minorminer/utils/chimera.py
minorminer/utils/feasibility.py
minorminer/utils/diagnostic.py
minorminer/src/pyutil.hpp
minorminer-0.2.19.dist-info/WHEEL
minorminer-0.2.19.dist-info/RECORD
minorminer-0.2.19.dist-info/top_level.txt
minorminer-0.2.19.dist-info/METADATA
minorminer-0.2.19.dist-info/licenses/LICENSE
