Metadata-Version: 2.4
Name: minorminer
Version: 0.2.19
Summary: Heuristic algorithm to find graph minor embeddings.
Author: Kelly Boothby
Maintainer-email: "D-Wave Inc." <tools@dwavesys.com>
License:                               Apache License
Project-URL: Homepage, https://github.com/dwavesystems/minorminer
Project-URL: Download, https://github.com/dwavesystems/minorminer/releases
Classifier: Operating System :: Microsoft :: Windows
Classifier: Operating System :: POSIX
Classifier: Operating System :: Unix
Classifier: Operating System :: MacOS
Classifier: Programming Language :: Python
Classifier: Programming Language :: Python :: 3
Classifier: Programming Language :: Python :: 3.9
Classifier: Programming Language :: Python :: 3.10
Classifier: Programming Language :: Python :: 3.11
Classifier: Programming Language :: Python :: 3.12
Classifier: Programming Language :: Python :: 3.13
Classifier: Programming Language :: Python :: 3 :: Only
Requires-Python: >=3.9
License-File: LICENSE
Requires-Dist: dwave-networkx>=0.8.13
Requires-Dist: fasteners>=0.15
Requires-Dist: homebase>=1.0.1
Requires-Dist: networkx>=2.4
Requires-Dist: numpy>=1.21.6
Requires-Dist: scipy>=1.7.3
Dynamic: license-file
